{
  "hash": "773f639672e4f236be79550f26b11a48",
  "result": {
    "engine": "knitr",
    "markdown": "---\ntitle: \"1995-03 Dashboard\"\nsubtitle: \"Monthly Dashboard for Beer sold at Dominick's: March 1995\"\ndraft: true\nformat:\n  html:\n    toc: true\n    toc-expand: 2\n\ncategories:\n  - Dominicks\n  - Beer\n  - 1995-03\n  - GEKS\n---\n\n\n\n# Overview\n\n\n\n::: {.cell}\n::: {.cell-output-display}\n\n```{=html}\n<div class=\"datatables html-widget html-fill-item\" id=\"htmlwidget-c8865715e4ba2392194d\" style=\"width:100%;height:auto;\"></div>\n<script type=\"application/json\" data-for=\"htmlwidget-c8865715e4ba2392194d\">{\"x\":{\"filter\":\"none\",\"vertical\":false,\"data\":[[\"1\",\"2\"],[\"YoY\",\"MoM\"],[1.092599266117731,1.062589375188735]],\"container\":\"<table class=\\\"display\\\">\\n  <thead>\\n    <tr>\\n      <th> <\\/th>\\n      <th>Metric<\\/th>\\n      <th>Value<\\/th>\\n    <\\/tr>\\n  <\\/thead>\\n<\\/table>\",\"options\":{\"dom\":\"t\",\"columnDefs\":[{\"className\":\"dt-right\",\"targets\":2},{\"orderable\":false,\"targets\":0},{\"name\":\" \",\"targets\":0},{\"name\":\"Metric\",\"targets\":1},{\"name\":\"Value\",\"targets\":2}],\"order\":[],\"autoWidth\":false,\"orderClasses\":false}},\"evals\":[],\"jsHooks\":[]}</script>\n```\n\n:::\n:::\n\n\n\n# Diagnostics\n\n## Analytical (output) diagnostics\n\n\n\n## Input diagnostics\n\n\n## Monitoring / data validation\n\n\n\n::: {.cell layout-align=\"center\"}\n::: {.cell-output-display}\n\n```{=html}\n<div class=\"plotly html-widget html-fill-item\" id=\"htmlwidget-50d19975ddea6f63abdd\" style=\"width:100%;height:520px;\"></div>\n<script type=\"application/json\" data-for=\"htmlwidget-50d19975ddea6f63abdd\">{\"x\":{\"data\":[{\"x\":[1,1,1,1,1,1,1,1,1,1,1,1,1,1,1,1,1,1,1,1,1,1,1,1,1,1,1,1,1,1,1,1,1,1,1,1,1,1,1,1,1,1,1,1,1,1],\"y\":[3,3,3,3,3,3,3,3,3,3,3,3,3,3,3,3,3,3,3,3,3,3,3,3,3,3,3,3,3,3,3,3,3,3,3,3,3,3,3,3,3,3,3,3,3,3],\"hoverinfo\":\"y\",\"type\":\"box\",\"fillcolor\":\"rgba(211,211,211,1)\",\"marker\":{\"opacity\":null,\"outliercolor\":\"rgba(0,0,0,1)\",\"line\":{\"width\":1.8897637795275593,\"color\":\"rgba(0,0,0,1)\"},\"size\":5.6692913385826778},\"line\":{\"color\":\"rgba(51,51,51,1)\",\"width\":1.8897637795275593},\"showlegend\":false,\"xaxis\":\"x\",\"yaxis\":\"y\",\"frame\":null},{\"x\":[1,1,1,1,1,1,1,1,1,1,1,1,1,1,1,1,1,1,1,1,1,1,1,1,1,1,1,1,1,1,1,1,1,1,1,1,1,1,1,1,1,1,1,1,1,1],\"y\":[288,242,282,248,281,259,269,281,285,287,248,270,282,264,270,284,264,287,294,303,287,263,282,295,298,309,293,305,287,291,301,327,341,323,293,316,322,333,350,328,347,327,335,350,352,336],\"hoverinfo\":\"y\",\"type\":\"box\",\"fillcolor\":\"rgba(211,211,211,1)\",\"marker\":{\"opacity\":null,\"outliercolor\":\"rgba(0,0,0,1)\",\"line\":{\"width\":1.8897637795275593,\"color\":\"rgba(0,0,0,1)\"},\"size\":5.6692913385826778},\"line\":{\"color\":\"rgba(51,51,51,1)\",\"width\":1.8897637795275593},\"showlegend\":false,\"xaxis\":\"x2\",\"yaxis\":\"y2\",\"frame\":null},{\"x\":[1,1,1,1,1,1,1,1,1,1,1,1,1,1,1,1,1,1,1,1,1,1,1,1,1,1,1,1,1,1,1,1,1,1,1,1,1,1,1,1,1,1,1,1,1,1],\"y\":[68,67,67,68,67,68,67,67,66,70,70,67,67,68,70,70,67,70,70,69,70,68,70,70,69,70,70,70,70,68,71,70,70,70,70,70,70,69,70,70,70,69,69,70,70,70],\"hoverinfo\":\"y\",\"type\":\"box\",\"fillcolor\":\"rgba(211,211,211,1)\",\"marker\":{\"opacity\":null,\"outliercolor\":\"rgba(0,0,0,1)\",\"line\":{\"width\":1.8897637795275593,\"color\":\"rgba(0,0,0,1)\"},\"size\":5.6692913385826778},\"line\":{\"color\":\"rgba(51,51,51,1)\",\"width\":1.8897637795275593},\"showlegend\":false,\"xaxis\":\"x3\",\"yaxis\":\"y3\",\"frame\":null},{\"x\":[1,1,1,1,1,1,1,1,1,1,1,1,1,1,1,1,1,1,1,1,1,1,1,1,1,1,1,1,1,1,1,1,1,1,1,1,1,1,1,1,1,1,1,1,1,1],\"y\":[276,278,278,259,310,274,288,302,308,262,265,305,307,304,280,316,316,299,309,301,316,334,284,310,324,314,323,309,313,365,315,325,339,349,367,319,318,365,346,359,342,348,342,355,345,337],\"hoverinfo\":\"y\",\"type\":\"box\",\"fillcolor\":\"rgba(211,211,211,1)\",\"marker\":{\"opacity\":null,\"outliercolor\":\"rgba(0,0,0,1)\",\"line\":{\"width\":1.8897637795275593,\"color\":\"rgba(0,0,0,1)\"},\"size\":5.6692913385826778},\"line\":{\"color\":\"rgba(51,51,51,1)\",\"width\":1.8897637795275593},\"showlegend\":false,\"xaxis\":\"x4\",\"yaxis\":\"y4\",\"frame\":null},{\"x\":[1,1,1,1,1,1,1,1,1,1,1,1,1,1,1,1,1,1,1,1,1,1,1,1,1,1,1,1,1,1,1,1,1,1,1,1,1,1,1,1,1,1,1,1,1,1],\"y\":[16,15,16,16,16,15,16,16,15,16,16,15,16,16,16,16,15,16,16,15,16,16,15,16,16,15,16,15,16,16,15,16,16,15,16,16,15,16,16,15,16,15,16,16,15,16],\"hoverinfo\":\"y\",\"type\":\"box\",\"fillcolor\":\"rgba(211,211,211,1)\",\"marker\":{\"opacity\":null,\"outliercolor\":\"rgba(0,0,0,1)\",\"line\":{\"width\":1.8897637795275593,\"color\":\"rgba(0,0,0,1)\"},\"size\":5.6692913385826778},\"line\":{\"color\":\"rgba(51,51,51,1)\",\"width\":1.8897637795275593},\"showlegend\":false,\"xaxis\":\"x5\",\"yaxis\":\"y5\",\"frame\":null},{\"x\":[1,1,1,1,1,1,1,1,1,1,1,1,1,1,1,1,1,1,1,1,1,1,1,1,1,1,1,1,1,1,1,1,1,1,1,1,1,1,1,1,1,1,1,1,1,1],\"y\":[21103,28587,30340,27581,31790,28556,28851,29327,35694,37395,37583,27634,32586,28306,28103,33418,29706,34711,16333,34494,41669,35084,28197,40755,31337,26598,16207,31271,35379,32810,33559,29921,39809,27447,39864,30575,29561,31731,28621,36987,32303,37533,36876,29948,23516,21086],\"hoverinfo\":\"y\",\"type\":\"box\",\"fillcolor\":\"rgba(211,211,211,1)\",\"marker\":{\"opacity\":null,\"outliercolor\":\"rgba(0,0,0,1)\",\"line\":{\"width\":1.8897637795275593,\"color\":\"rgba(0,0,0,1)\"},\"size\":5.6692913385826778},\"line\":{\"color\":\"rgba(51,51,51,1)\",\"width\":1.8897637795275593},\"showlegend\":false,\"xaxis\":\"x6\",\"yaxis\":\"y6\",\"frame\":null},{\"x\":[1,1,1,1,1,1,1,1,1,1,1,1,1,1,1,1,1,1,1,1,1,1,1,1,1,1,1,1,1,1,1,1,1,1,1,1,1,1,1,1,1,1,1,1,1,1],\"y\":[4,4,5,5,5,3,4,5,4,4,4,4,4,4,5,5,4,4,5,4,4,4,5,4,5,3,5,4,4,5,5,4,4,5,4,2,4,4,4,4,2,3,4,5,5,4],\"hoverinfo\":\"y\",\"type\":\"box\",\"fillcolor\":\"rgba(211,211,211,1)\",\"marker\":{\"opacity\":null,\"outliercolor\":\"rgba(0,0,0,1)\",\"line\":{\"width\":1.8897637795275593,\"color\":\"rgba(0,0,0,1)\"},\"size\":5.6692913385826778},\"line\":{\"color\":\"rgba(51,51,51,1)\",\"width\":1.8897637795275593},\"showlegend\":false,\"xaxis\":\"x7\",\"yaxis\":\"y7\",\"frame\":null},{\"x\":[1,1,1,1,1,1,1,1,1,1,1,1,1,1,1,1,1,1,1,1,1,1,1,1,1,1,1,1,1,1,1,1,1,1,1,1,1,1,1,1,1,1,1,1,1,1],\"y\":[1496032.3400000001,1328069.28,2067518.2400000002,1114092.7200000002,1271414.6700000002,1372604.9300000002,1028935.7400000001,1060401.4199999999,1021995.87,1349736.1800000002,1504780.8900000001,995900.69000000006,1531602.6900000002,1283293.1500000001,1046789.8200000001,1318835.5800000001,1020731.76,1079786.25,1058049.3200000001,1168524.78,1880474.6000000001,1439483.8,1345932.3200000001,1465307.5900000001,658666.01000000001,1141795.0900000001,1141909.8400000001,1054486.5700000001,1252306.6500000001,819053.96000000008,2126082.1900000004,2274705.9500000002,1541614.9100000001,1331705.99,1861821.9100000001,1251098.55,1034468.4700000001,1432246.04,1696781.9600000002,1774270.6400000001,1286656.2600000009,1320612.1600000001,915204.26000000001,750498.32000000007,1146287.6900000002,1615666.8200000001],\"hoverinfo\":\"y\",\"type\":\"box\",\"fillcolor\":\"rgba(211,211,211,1)\",\"marker\":{\"opacity\":null,\"outliercolor\":\"rgba(0,0,0,1)\",\"line\":{\"width\":1.8897637795275593,\"color\":\"rgba(0,0,0,1)\"},\"size\":5.6692913385826778},\"line\":{\"color\":\"rgba(51,51,51,1)\",\"width\":1.8897637795275593},\"showlegend\":false,\"xaxis\":\"x8\",\"yaxis\":\"y8\",\"frame\":null},{\"x\":[0.40000000000000002,1.6000000000000001],\"y\":[3,3],\"text\":\"Value:       3\",\"type\":\"scatter\",\"mode\":\"lines\",\"line\":{\"width\":3.7795275590551185,\"color\":\"rgba(255,0,0,1)\",\"dash\":\"dash\"},\"hoveron\":\"points\",\"showlegend\":false,\"xaxis\":\"x\",\"yaxis\":\"y\",\"hoverinfo\":\"text\",\"frame\":null},{\"x\":[0.40000000000000002,1.6000000000000001],\"y\":[350,350],\"text\":\"Value:     350\",\"type\":\"scatter\",\"mode\":\"lines\",\"line\":{\"width\":3.7795275590551185,\"color\":\"rgba(255,0,0,1)\",\"dash\":\"dash\"},\"hoveron\":\"points\",\"showlegend\":false,\"xaxis\":\"x2\",\"yaxis\":\"y2\",\"hoverinfo\":\"text\",\"frame\":null},{\"x\":[0.40000000000000002,1.6000000000000001],\"y\":[69,69],\"text\":\"Value:      69\",\"type\":\"scatter\",\"mode\":\"lines\",\"line\":{\"width\":3.7795275590551185,\"color\":\"rgba(255,0,0,1)\",\"dash\":\"dash\"},\"hoveron\":\"points\",\"showlegend\":false,\"xaxis\":\"x3\",\"yaxis\":\"y3\",\"hoverinfo\":\"text\",\"frame\":null},{\"x\":[0.40000000000000002,1.6000000000000001],\"y\":[365,365],\"text\":\"Value:     365\",\"type\":\"scatter\",\"mode\":\"lines\",\"line\":{\"width\":3.7795275590551185,\"color\":\"rgba(255,0,0,1)\",\"dash\":\"dash\"},\"hoveron\":\"points\",\"showlegend\":false,\"xaxis\":\"x4\",\"yaxis\":\"y4\",\"hoverinfo\":\"text\",\"frame\":null},{\"x\":[0.40000000000000002,1.6000000000000001],\"y\":[16,16],\"text\":\"Value:      16\",\"type\":\"scatter\",\"mode\":\"lines\",\"line\":{\"width\":3.7795275590551185,\"color\":\"rgba(255,0,0,1)\",\"dash\":\"dash\"},\"hoveron\":\"points\",\"showlegend\":false,\"xaxis\":\"x5\",\"yaxis\":\"y5\",\"hoverinfo\":\"text\",\"frame\":null},{\"x\":[0.40000000000000002,1.6000000000000001],\"y\":[32303,32303],\"text\":\"Value:   32303\",\"type\":\"scatter\",\"mode\":\"lines\",\"line\":{\"width\":3.7795275590551185,\"color\":\"rgba(255,0,0,1)\",\"dash\":\"dash\"},\"hoveron\":\"points\",\"showlegend\":false,\"xaxis\":\"x6\",\"yaxis\":\"y6\",\"hoverinfo\":\"text\",\"frame\":null},{\"x\":[0.40000000000000002,1.6000000000000001],\"y\":[4,4],\"text\":\"Value:       4\",\"type\":\"scatter\",\"mode\":\"lines\",\"line\":{\"width\":3.7795275590551185,\"color\":\"rgba(255,0,0,1)\",\"dash\":\"dash\"},\"hoveron\":\"points\",\"showlegend\":false,\"xaxis\":\"x7\",\"yaxis\":\"y7\",\"hoverinfo\":\"text\",\"frame\":null},{\"x\":[0.40000000000000002,1.6000000000000001],\"y\":[1146287.6900000002,1146287.6900000002],\"text\":\"Value: 1146288\",\"type\":\"scatter\",\"mode\":\"lines\",\"line\":{\"width\":3.7795275590551185,\"color\":\"rgba(255,0,0,1)\",\"dash\":\"dash\"},\"hoveron\":\"points\",\"showlegend\":false,\"xaxis\":\"x8\",\"yaxis\":\"y8\",\"hoverinfo\":\"text\",\"frame\":null}],\"layout\":{\"margin\":{\"t\":52.529680365296812,\"r\":7.3059360730593621,\"b\":10.958904109589042,\"l\":54.794520547945211},\"paper_bgcolor\":\"rgba(255,255,255,1)\",\"font\":{\"color\":\"rgba(0,0,0,1)\",\"family\":\"\",\"size\":14.611872146118724},\"title\":{\"text\":\"Key monitoring metrics, focus on 1995-03\",\"font\":{\"color\":\"rgba(0,0,0,1)\",\"family\":\"\",\"size\":17.534246575342465},\"x\":0,\"xref\":\"paper\"},\"xaxis\":{\"domain\":[0,0.30235159817351598],\"automargin\":true,\"type\":\"linear\",\"autorange\":false,\"range\":[0.40000000000000002,1.6000000000000001],\"tickmode\":\"array\",\"ticktext\":[\"distinct_com_codes\"],\"tickvals\":[1],\"categoryorder\":\"array\",\"categoryarray\":[\"distinct_com_codes\"],\"nticks\":null,\"ticks\":\"\",\"tickcolor\":null,\"ticklen\":3.6529680365296811,\"tickwidth\":0,\"showticklabels\":false,\"tickfont\":{\"color\":null,\"family\":null,\"size\":0},\"tickangle\":-0,\"showline\":false,\"linecolor\":null,\"linewidth\":0,\"showgrid\":true,\"gridcolor\":\"rgba(235,235,235,1)\",\"gridwidth\":0,\"zeroline\":false,\"anchor\":\"y\",\"title\":\"\",\"hoverformat\":\".2f\"},\"yaxis\":{\"domain\":[0.6911244292237444,1],\"automargin\":true,\"type\":\"linear\",\"autorange\":false,\"range\":[2.9500000000000002,3.0499999999999998],\"tickmode\":\"array\",\"ticktext\":[\"2.950\",\"2.975\",\"3.000\",\"3.025\"],\"tickvals\":[2.9500000000000002,2.9750000000000001,3,3.0250000000000004],\"categoryorder\":\"array\",\"categoryarray\":[\"2.950\",\"2.975\",\"3.000\",\"3.025\"],\"nticks\":null,\"ticks\":\"\",\"tickcolor\":null,\"ticklen\":3.6529680365296811,\"tickwidth\":0,\"showticklabels\":true,\"tickfont\":{\"color\":\"rgba(77,77,77,1)\",\"family\":\"\",\"size\":11.68949771689498},\"tickangle\":-0,\"showline\":false,\"linecolor\":null,\"linewidth\":0,\"showgrid\":true,\"gridcolor\":\"rgba(235,235,235,1)\",\"gridwidth\":0,\"zeroline\":false,\"anchor\":\"x\",\"title\":\"\",\"hoverformat\":\".2f\"},\"annotations\":[{\"text\":\"Value\",\"x\":0,\"y\":0.5,\"showarrow\":false,\"ax\":0,\"ay\":0,\"font\":{\"color\":\"rgba(0,0,0,1)\",\"family\":\"\",\"size\":14.611872146118724},\"xref\":\"paper\",\"yref\":\"paper\",\"textangle\":-90,\"xanchor\":\"right\",\"yanchor\":\"center\",\"annotationType\":\"axis\",\"xshift\":-39.452054794520549},{\"text\":\"distinct_com_codes\",\"x\":0.15117579908675799,\"y\":1,\"showarrow\":false,\"ax\":0,\"ay\":0,\"font\":{\"color\":\"rgba(26,26,26,1)\",\"family\":\"\",\"size\":11.689497716894984},\"xref\":\"paper\",\"yref\":\"paper\",\"textangle\":-0,\"xanchor\":\"center\",\"yanchor\":\"bottom\"},{\"text\":\"distinct_nitems\",\"x\":0.49999999999999994,\"y\":1,\"showarrow\":false,\"ax\":0,\"ay\":0,\"font\":{\"color\":\"rgba(26,26,26,1)\",\"family\":\"\",\"size\":11.689497716894984},\"xref\":\"paper\",\"yref\":\"paper\",\"textangle\":-0,\"xanchor\":\"center\",\"yanchor\":\"bottom\"},{\"text\":\"distinct_stores\",\"x\":0.84882420091324207,\"y\":1,\"showarrow\":false,\"ax\":0,\"ay\":0,\"font\":{\"color\":\"rgba(26,26,26,1)\",\"family\":\"\",\"size\":11.689497716894984},\"xref\":\"paper\",\"yref\":\"paper\",\"textangle\":-0,\"xanchor\":\"center\",\"yanchor\":\"bottom\"},{\"text\":\"distinct_upcs\",\"x\":0.15117579908675799,\"y\":0.64220890410958908,\"showarrow\":false,\"ax\":0,\"ay\":0,\"font\":{\"color\":\"rgba(26,26,26,1)\",\"family\":\"\",\"size\":11.689497716894984},\"xref\":\"paper\",\"yref\":\"paper\",\"textangle\":-0,\"xanchor\":\"center\",\"yanchor\":\"bottom\"},{\"text\":\"distinct_zones\",\"x\":0.49999999999999994,\"y\":0.64220890410958908,\"showarrow\":false,\"ax\":0,\"ay\":0,\"font\":{\"color\":\"rgba(26,26,26,1)\",\"family\":\"\",\"size\":11.689497716894984},\"xref\":\"paper\",\"yref\":\"paper\",\"textangle\":-0,\"xanchor\":\"center\",\"yanchor\":\"bottom\"},{\"text\":\"number_of_rows\",\"x\":0.84882420091324207,\"y\":0.64220890410958908,\"showarrow\":false,\"ax\":0,\"ay\":0,\"font\":{\"color\":\"rgba(26,26,26,1)\",\"family\":\"\",\"size\":11.689497716894984},\"xref\":\"paper\",\"yref\":\"paper\",\"textangle\":-0,\"xanchor\":\"center\",\"yanchor\":\"bottom\"},{\"text\":\"number_of_weeks\",\"x\":0.15117579908675799,\"y\":0.30887557077625571,\"showarrow\":false,\"ax\":0,\"ay\":0,\"font\":{\"color\":\"rgba(26,26,26,1)\",\"family\":\"\",\"size\":11.689497716894984},\"xref\":\"paper\",\"yref\":\"paper\",\"textangle\":-0,\"xanchor\":\"center\",\"yanchor\":\"bottom\"},{\"text\":\"total_sales\",\"x\":0.49999999999999994,\"y\":0.30887557077625571,\"showarrow\":false,\"ax\":0,\"ay\":0,\"font\":{\"color\":\"rgba(26,26,26,1)\",\"family\":\"\",\"size\":11.689497716894984},\"xref\":\"paper\",\"yref\":\"paper\",\"textangle\":-0,\"xanchor\":\"center\",\"yanchor\":\"bottom\"}],\"shapes\":[{\"type\":\"rect\",\"fillcolor\":null,\"line\":{\"color\":null,\"width\":0,\"linetype\":[]},\"yref\":\"paper\",\"xref\":\"paper\",\"layer\":\"below\",\"x0\":0,\"x1\":0.30235159817351598,\"y0\":0.6911244292237444,\"y1\":1},{\"type\":\"rect\",\"fillcolor\":null,\"line\":{\"color\":null,\"width\":0,\"linetype\":[]},\"yref\":\"paper\",\"xref\":\"paper\",\"layer\":\"below\",\"x0\":0,\"x1\":0.30235159817351598,\"y0\":0,\"y1\":23.37899543378996,\"yanchor\":1,\"ysizemode\":\"pixel\"},{\"type\":\"rect\",\"fillcolor\":null,\"line\":{\"color\":null,\"width\":0,\"linetype\":[]},\"yref\":\"paper\",\"xref\":\"paper\",\"layer\":\"below\",\"x0\":0.36431506849315065,\"x1\":0.63568493150684924,\"y0\":0.6911244292237444,\"y1\":1},{\"type\":\"rect\",\"fillcolor\":null,\"line\":{\"color\":null,\"width\":0,\"linetype\":[]},\"yref\":\"paper\",\"xref\":\"paper\",\"layer\":\"below\",\"x0\":0.36431506849315065,\"x1\":0.63568493150684924,\"y0\":0,\"y1\":23.37899543378996,\"yanchor\":1,\"ysizemode\":\"pixel\"},{\"type\":\"rect\",\"fillcolor\":null,\"line\":{\"color\":null,\"width\":0,\"linetype\":[]},\"yref\":\"paper\",\"xref\":\"paper\",\"layer\":\"below\",\"x0\":0.69764840182648402,\"x1\":1,\"y0\":0.6911244292237444,\"y1\":1},{\"type\":\"rect\",\"fillcolor\":null,\"line\":{\"color\":null,\"width\":0,\"linetype\":[]},\"yref\":\"paper\",\"xref\":\"paper\",\"layer\":\"below\",\"x0\":0.69764840182648402,\"x1\":1,\"y0\":0,\"y1\":23.37899543378996,\"yanchor\":1,\"ysizemode\":\"pixel\"},{\"type\":\"rect\",\"fillcolor\":null,\"line\":{\"color\":null,\"width\":0,\"linetype\":[]},\"yref\":\"paper\",\"xref\":\"paper\",\"layer\":\"below\",\"x0\":0,\"x1\":0.30235159817351598,\"y0\":0.35779109589041103,\"y1\":0.64220890410958908},{\"type\":\"rect\",\"fillcolor\":null,\"line\":{\"color\":null,\"width\":0,\"linetype\":[]},\"yref\":\"paper\",\"xref\":\"paper\",\"layer\":\"below\",\"x0\":0,\"x1\":0.30235159817351598,\"y0\":0,\"y1\":23.37899543378996,\"yanchor\":0.64220890410958908,\"ysizemode\":\"pixel\"},{\"type\":\"rect\",\"fillcolor\":null,\"line\":{\"color\":null,\"width\":0,\"linetype\":[]},\"yref\":\"paper\",\"xref\":\"paper\",\"layer\":\"below\",\"x0\":0.36431506849315065,\"x1\":0.63568493150684924,\"y0\":0.35779109589041103,\"y1\":0.64220890410958908},{\"type\":\"rect\",\"fillcolor\":null,\"line\":{\"color\":null,\"width\":0,\"linetype\":[]},\"yref\":\"paper\",\"xref\":\"paper\",\"layer\":\"below\",\"x0\":0.36431506849315065,\"x1\":0.63568493150684924,\"y0\":0,\"y1\":23.37899543378996,\"yanchor\":0.64220890410958908,\"ysizemode\":\"pixel\"},{\"type\":\"rect\",\"fillcolor\":null,\"line\":{\"color\":null,\"width\":0,\"linetype\":[]},\"yref\":\"paper\",\"xref\":\"paper\",\"layer\":\"below\",\"x0\":0.69764840182648402,\"x1\":1,\"y0\":0.35779109589041103,\"y1\":0.64220890410958908},{\"type\":\"rect\",\"fillcolor\":null,\"line\":{\"color\":null,\"width\":0,\"linetype\":[]},\"yref\":\"paper\",\"xref\":\"paper\",\"layer\":\"below\",\"x0\":0.69764840182648402,\"x1\":1,\"y0\":0,\"y1\":23.37899543378996,\"yanchor\":0.64220890410958908,\"ysizemode\":\"pixel\"},{\"type\":\"rect\",\"fillcolor\":null,\"line\":{\"color\":null,\"width\":0,\"linetype\":[]},\"yref\":\"paper\",\"xref\":\"paper\",\"layer\":\"below\",\"x0\":0,\"x1\":0.30235159817351598,\"y0\":0,\"y1\":0.30887557077625571},{\"type\":\"rect\",\"fillcolor\":null,\"line\":{\"color\":null,\"width\":0,\"linetype\":[]},\"yref\":\"paper\",\"xref\":\"paper\",\"layer\":\"below\",\"x0\":0,\"x1\":0.30235159817351598,\"y0\":0,\"y1\":23.37899543378996,\"yanchor\":0.30887557077625571,\"ysizemode\":\"pixel\"},{\"type\":\"rect\",\"fillcolor\":null,\"line\":{\"color\":null,\"width\":0,\"linetype\":[]},\"yref\":\"paper\",\"xref\":\"paper\",\"layer\":\"below\",\"x0\":0.36431506849315065,\"x1\":0.63568493150684924,\"y0\":0,\"y1\":0.30887557077625571},{\"type\":\"rect\",\"fillcolor\":null,\"line\":{\"color\":null,\"width\":0,\"linetype\":[]},\"yref\":\"paper\",\"xref\":\"paper\",\"layer\":\"below\",\"x0\":0.36431506849315065,\"x1\":0.63568493150684924,\"y0\":0,\"y1\":23.37899543378996,\"yanchor\":0.30887557077625571,\"ysizemode\":\"pixel\"}],\"xaxis2\":{\"type\":\"linear\",\"autorange\":false,\"range\":[0.40000000000000002,1.6000000000000001],\"tickmode\":\"array\",\"ticktext\":[\"distinct_nitems\"],\"tickvals\":[1],\"categoryorder\":\"array\",\"categoryarray\":[\"distinct_nitems\"],\"nticks\":null,\"ticks\":\"\",\"tickcolor\":null,\"ticklen\":3.6529680365296811,\"tickwidth\":0,\"showticklabels\":false,\"tickfont\":{\"color\":null,\"family\":null,\"size\":0},\"tickangle\":-0,\"showline\":false,\"linecolor\":null,\"linewidth\":0,\"showgrid\":true,\"domain\":[0.36431506849315065,0.63568493150684924],\"gridcolor\":\"rgba(235,235,235,1)\",\"gridwidth\":0,\"zeroline\":false,\"anchor\":\"y2\",\"title\":\"\",\"hoverformat\":\".2f\"},\"yaxis2\":{\"type\":\"linear\",\"autorange\":false,\"range\":[236.5,357.5],\"tickmode\":\"array\",\"ticktext\":[\"240\",\"270\",\"300\",\"330\"],\"tickvals\":[240,270,300,330],\"categoryorder\":\"array\",\"categoryarray\":[\"240\",\"270\",\"300\",\"330\"],\"nticks\":null,\"ticks\":\"\",\"tickcolor\":null,\"ticklen\":3.6529680365296811,\"tickwidth\":0,\"showticklabels\":true,\"tickfont\":{\"color\":\"rgba(77,77,77,1)\",\"family\":\"\",\"size\":11.68949771689498},\"tickangle\":-0,\"showline\":false,\"linecolor\":null,\"linewidth\":0,\"showgrid\":true,\"domain\":[0.6911244292237444,1],\"gridcolor\":\"rgba(235,235,235,1)\",\"gridwidth\":0,\"zeroline\":false,\"anchor\":\"x2\",\"title\":\"\",\"hoverformat\":\".2f\"},\"xaxis3\":{\"type\":\"linear\",\"autorange\":false,\"range\":[0.40000000000000002,1.6000000000000001],\"tickmode\":\"array\",\"ticktext\":[\"distinct_stores\"],\"tickvals\":[1],\"categoryorder\":\"array\",\"categoryarray\":[\"distinct_stores\"],\"nticks\":null,\"ticks\":\"\",\"tickcolor\":null,\"ticklen\":3.6529680365296811,\"tickwidth\":0,\"showticklabels\":false,\"tickfont\":{\"color\":null,\"family\":null,\"size\":0},\"tickangle\":-0,\"showline\":false,\"linecolor\":null,\"linewidth\":0,\"showgrid\":true,\"domain\":[0.69764840182648402,1],\"gridcolor\":\"rgba(235,235,235,1)\",\"gridwidth\":0,\"zeroline\":false,\"anchor\":\"y3\",\"title\":\"\",\"hoverformat\":\".2f\"},\"yaxis3\":{\"type\":\"linear\",\"autorange\":false,\"range\":[65.75,71.25],\"tickmode\":\"array\",\"ticktext\":[\"66\",\"67\",\"68\",\"69\",\"70\",\"71\"],\"tickvals\":[66,67,68,69,70,71],\"categoryorder\":\"array\",\"categoryarray\":[\"66\",\"67\",\"68\",\"69\",\"70\",\"71\"],\"nticks\":null,\"ticks\":\"\",\"tickcolor\":null,\"ticklen\":3.6529680365296811,\"tickwidth\":0,\"showticklabels\":true,\"tickfont\":{\"color\":\"rgba(77,77,77,1)\",\"family\":\"\",\"size\":11.68949771689498},\"tickangle\":-0,\"showline\":false,\"linecolor\":null,\"linewidth\":0,\"showgrid\":true,\"domain\":[0.6911244292237444,1],\"gridcolor\":\"rgba(235,235,235,1)\",\"gridwidth\":0,\"zeroline\":false,\"anchor\":\"x3\",\"title\":\"\",\"hoverformat\":\".2f\"},\"xaxis4\":{\"type\":\"linear\",\"autorange\":false,\"range\":[0.40000000000000002,1.6000000000000001],\"tickmode\":\"array\",\"ticktext\":[\"distinct_upcs\"],\"tickvals\":[1],\"categoryorder\":\"array\",\"categoryarray\":[\"distinct_upcs\"],\"nticks\":null,\"ticks\":\"\",\"tickcolor\":null,\"ticklen\":3.6529680365296811,\"tickwidth\":0,\"showticklabels\":false,\"tickfont\":{\"color\":null,\"family\":null,\"size\":0},\"tickangle\":-0,\"showline\":false,\"linecolor\":null,\"linewidth\":0,\"showgrid\":true,\"domain\":[0,0.30235159817351598],\"gridcolor\":\"rgba(235,235,235,1)\",\"gridwidth\":0,\"zeroline\":false,\"anchor\":\"y4\",\"title\":\"\",\"hoverformat\":\".2f\"},\"yaxis4\":{\"type\":\"linear\",\"autorange\":false,\"range\":[253.59999999999999,372.39999999999998],\"tickmode\":\"array\",\"ticktext\":[\"275\",\"300\",\"325\",\"350\"],\"tickvals\":[275,300,325,350],\"categoryorder\":\"array\",\"categoryarray\":[\"275\",\"300\",\"325\",\"350\"],\"nticks\":null,\"ticks\":\"\",\"tickcolor\":null,\"ticklen\":3.6529680365296811,\"tickwidth\":0,\"showticklabels\":true,\"tickfont\":{\"color\":\"rgba(77,77,77,1)\",\"family\":\"\",\"size\":11.68949771689498},\"tickangle\":-0,\"showline\":false,\"linecolor\":null,\"linewidth\":0,\"showgrid\":true,\"domain\":[0.35779109589041103,0.64220890410958908],\"gridcolor\":\"rgba(235,235,235,1)\",\"gridwidth\":0,\"zeroline\":false,\"anchor\":\"x4\",\"title\":\"\",\"hoverformat\":\".2f\"},\"xaxis5\":{\"type\":\"linear\",\"autorange\":false,\"range\":[0.40000000000000002,1.6000000000000001],\"tickmode\":\"array\",\"ticktext\":[\"distinct_zones\"],\"tickvals\":[1],\"categoryorder\":\"array\",\"categoryarray\":[\"distinct_zones\"],\"nticks\":null,\"ticks\":\"\",\"tickcolor\":null,\"ticklen\":3.6529680365296811,\"tickwidth\":0,\"showticklabels\":false,\"tickfont\":{\"color\":null,\"family\":null,\"size\":0},\"tickangle\":-0,\"showline\":false,\"linecolor\":null,\"linewidth\":0,\"showgrid\":true,\"domain\":[0.36431506849315065,0.63568493150684924],\"gridcolor\":\"rgba(235,235,235,1)\",\"gridwidth\":0,\"zeroline\":false,\"anchor\":\"y5\",\"title\":\"\",\"hoverformat\":\".2f\"},\"yaxis5\":{\"type\":\"linear\",\"autorange\":false,\"range\":[14.949999999999999,16.050000000000001],\"tickmode\":\"array\",\"ticktext\":[\"15.00\",\"15.25\",\"15.50\",\"15.75\",\"16.00\"],\"tickvals\":[15,15.25,15.5,15.75,16],\"categoryorder\":\"array\",\"categoryarray\":[\"15.00\",\"15.25\",\"15.50\",\"15.75\",\"16.00\"],\"nticks\":null,\"ticks\":\"\",\"tickcolor\":null,\"ticklen\":3.6529680365296811,\"tickwidth\":0,\"showticklabels\":true,\"tickfont\":{\"color\":\"rgba(77,77,77,1)\",\"family\":\"\",\"size\":11.68949771689498},\"tickangle\":-0,\"showline\":false,\"linecolor\":null,\"linewidth\":0,\"showgrid\":true,\"domain\":[0.35779109589041103,0.64220890410958908],\"gridcolor\":\"rgba(235,235,235,1)\",\"gridwidth\":0,\"zeroline\":false,\"anchor\":\"x5\",\"title\":\"\",\"hoverformat\":\".2f\"},\"xaxis6\":{\"type\":\"linear\",\"autorange\":false,\"range\":[0.40000000000000002,1.6000000000000001],\"tickmode\":\"array\",\"ticktext\":[\"number_of_rows\"],\"tickvals\":[1],\"categoryorder\":\"array\",\"categoryarray\":[\"number_of_rows\"],\"nticks\":null,\"ticks\":\"\",\"tickcolor\":null,\"ticklen\":3.6529680365296811,\"tickwidth\":0,\"showticklabels\":false,\"tickfont\":{\"color\":null,\"family\":null,\"size\":0},\"tickangle\":-0,\"showline\":false,\"linecolor\":null,\"linewidth\":0,\"showgrid\":true,\"domain\":[0.69764840182648402,1],\"gridcolor\":\"rgba(235,235,235,1)\",\"gridwidth\":0,\"zeroline\":false,\"anchor\":\"y6\",\"title\":\"\",\"hoverformat\":\".2f\"},\"yaxis6\":{\"type\":\"linear\",\"autorange\":false,\"range\":[14933.9,42942.099999999999],\"tickmode\":\"array\",\"ticktext\":[\"15000\",\"20000\",\"25000\",\"30000\",\"35000\",\"40000\"],\"tickvals\":[15000,20000,25000,30000,35000,40000],\"categoryorder\":\"array\",\"categoryarray\":[\"15000\",\"20000\",\"25000\",\"30000\",\"35000\",\"40000\"],\"nticks\":null,\"ticks\":\"\",\"tickcolor\":null,\"ticklen\":3.6529680365296811,\"tickwidth\":0,\"showticklabels\":true,\"tickfont\":{\"color\":\"rgba(77,77,77,1)\",\"family\":\"\",\"size\":11.68949771689498},\"tickangle\":-0,\"showline\":false,\"linecolor\":null,\"linewidth\":0,\"showgrid\":true,\"domain\":[0.35779109589041103,0.64220890410958908],\"gridcolor\":\"rgba(235,235,235,1)\",\"gridwidth\":0,\"zeroline\":false,\"anchor\":\"x6\",\"title\":\"\",\"hoverformat\":\".2f\"},\"xaxis7\":{\"type\":\"linear\",\"autorange\":false,\"range\":[0.40000000000000002,1.6000000000000001],\"tickmode\":\"array\",\"ticktext\":[\"number_of_weeks\"],\"tickvals\":[1],\"categoryorder\":\"array\",\"categoryarray\":[\"number_of_weeks\"],\"nticks\":null,\"ticks\":\"\",\"tickcolor\":null,\"ticklen\":3.6529680365296811,\"tickwidth\":0,\"showticklabels\":false,\"tickfont\":{\"color\":null,\"family\":null,\"size\":0},\"tickangle\":-0,\"showline\":false,\"linecolor\":null,\"linewidth\":0,\"showgrid\":true,\"domain\":[0,0.30235159817351598],\"gridcolor\":\"rgba(235,235,235,1)\",\"gridwidth\":0,\"zeroline\":false,\"anchor\":\"y7\",\"title\":\"\",\"hoverformat\":\".2f\"},\"yaxis7\":{\"type\":\"linear\",\"autorange\":false,\"range\":[1.8500000000000001,5.1500000000000004],\"tickmode\":\"array\",\"ticktext\":[\"2\",\"3\",\"4\",\"5\"],\"tickvals\":[2,3,4,5],\"categoryorder\":\"array\",\"categoryarray\":[\"2\",\"3\",\"4\",\"5\"],\"nticks\":null,\"ticks\":\"\",\"tickcolor\":null,\"ticklen\":3.6529680365296811,\"tickwidth\":0,\"showticklabels\":true,\"tickfont\":{\"color\":\"rgba(77,77,77,1)\",\"family\":\"\",\"size\":11.68949771689498},\"tickangle\":-0,\"showline\":false,\"linecolor\":null,\"linewidth\":0,\"showgrid\":true,\"domain\":[0,0.30887557077625571],\"gridcolor\":\"rgba(235,235,235,1)\",\"gridwidth\":0,\"zeroline\":false,\"anchor\":\"x7\",\"title\":\"\",\"hoverformat\":\".2f\"},\"xaxis8\":{\"type\":\"linear\",\"autorange\":false,\"range\":[0.40000000000000002,1.6000000000000001],\"tickmode\":\"array\",\"ticktext\":[\"total_sales\"],\"tickvals\":[1],\"categoryorder\":\"array\",\"categoryarray\":[\"total_sales\"],\"nticks\":null,\"ticks\":\"\",\"tickcolor\":null,\"ticklen\":3.6529680365296811,\"tickwidth\":0,\"showticklabels\":false,\"tickfont\":{\"color\":null,\"family\":null,\"size\":0},\"tickangle\":-0,\"showline\":false,\"linecolor\":null,\"linewidth\":0,\"showgrid\":true,\"domain\":[0.36431506849315065,0.63568493150684924],\"gridcolor\":\"rgba(235,235,235,1)\",\"gridwidth\":0,\"zeroline\":false,\"anchor\":\"y8\",\"title\":\"\",\"hoverformat\":\".2f\"},\"yaxis8\":{\"type\":\"linear\",\"autorange\":false,\"range\":[577864.01300000004,2355507.9470000002],\"tickmode\":\"array\",\"ticktext\":[\"1000000\",\"1500000\",\"2000000\"],\"tickvals\":[1000000,1500000,2000000],\"categoryorder\":\"array\",\"categoryarray\":[\"1000000\",\"1500000\",\"2000000\"],\"nticks\":null,\"ticks\":\"\",\"tickcolor\":null,\"ticklen\":3.6529680365296811,\"tickwidth\":0,\"showticklabels\":true,\"tickfont\":{\"color\":\"rgba(77,77,77,1)\",\"family\":\"\",\"size\":11.68949771689498},\"tickangle\":-0,\"showline\":false,\"linecolor\":null,\"linewidth\":0,\"showgrid\":true,\"domain\":[0,0.30887557077625571],\"gridcolor\":\"rgba(235,235,235,1)\",\"gridwidth\":0,\"zeroline\":false,\"anchor\":\"x8\",\"title\":\"\",\"hoverformat\":\".2f\"},\"showlegend\":false,\"legend\":{\"bgcolor\":null,\"bordercolor\":null,\"borderwidth\":0,\"font\":{\"color\":\"rgba(0,0,0,1)\",\"family\":\"\",\"size\":11.689497716894984}},\"hovermode\":\"closest\",\"barmode\":\"relative\"},\"config\":{\"doubleClick\":\"reset\",\"modeBarButtonsToAdd\":[\"hoverclosest\",\"hovercompare\"],\"showSendToCloud\":false},\"source\":\"A\",\"attrs\":{\"69181974601\":{\"x\":{},\"y\":{},\"type\":\"box\"},\"6918772768f4\":{\"yintercept\":{}}},\"cur_data\":\"69181974601\",\"visdat\":{\"69181974601\":[\"function (y) \",\"x\"],\"6918772768f4\":[\"function (y) \",\"x\"]},\"highlight\":{\"on\":\"plotly_click\",\"persistent\":false,\"dynamic\":false,\"selectize\":false,\"opacityDim\":0.20000000000000001,\"selected\":{\"opacity\":1},\"debounce\":0},\"shinyEvents\":[\"plotly_hover\",\"plotly_click\",\"plotly_selected\",\"plotly_relayout\",\"plotly_brushed\",\"plotly_brushing\",\"plotly_clickannotation\",\"plotly_doubleclick\",\"plotly_deselect\",\"plotly_afterplot\",\"plotly_sunburstclick\"],\"base_url\":\"https://plot.ly\"},\"evals\":[],\"jsHooks\":[]}</script>\n```\n\n:::\n:::",
    "supporting": [
      "dominicks-ber-1995-03_files"
    ],
    "filters": [
      "rmarkdown/pagebreak.lua"
    ],
    "includes": {
      "include-in-header": [
        "<link href=\"../../../site_libs/htmltools-fill-0.5.8.1/fill.css\" rel=\"stylesheet\" />\n<script src=\"../../../site_libs/htmlwidgets-1.6.4/htmlwidgets.js\"></script>\n<link href=\"../../../site_libs/datatables-css-0.0.0/datatables-crosstalk.css\" rel=\"stylesheet\" />\n<script src=\"../../../site_libs/datatables-binding-0.34.0/datatables.js\"></script>\n<script src=\"../../../site_libs/jquery-3.6.0/jquery-3.6.0.min.js\"></script>\n<link href=\"../../../site_libs/dt-core-1.13.6/css/jquery.dataTables.min.css\" rel=\"stylesheet\" />\n<link href=\"../../../site_libs/dt-core-1.13.6/css/jquery.dataTables.extra.css\" rel=\"stylesheet\" />\n<script src=\"../../../site_libs/dt-core-1.13.6/js/jquery.dataTables.min.js\"></script>\n<link href=\"../../../site_libs/crosstalk-1.2.2/css/crosstalk.min.css\" rel=\"stylesheet\" />\n<script src=\"../../../site_libs/crosstalk-1.2.2/js/crosstalk.min.js\"></script>\n<script src=\"../../../site_libs/plotly-binding-4.11.0/plotly.js\"></script>\n<script src=\"../../../site_libs/typedarray-0.1/typedarray.min.js\"></script>\n<link href=\"../../../site_libs/plotly-htmlwidgets-css-2.11.1/plotly-htmlwidgets.css\" rel=\"stylesheet\" />\n<script src=\"../../../site_libs/plotly-main-2.11.1/plotly-latest.min.js\"></script>\n"
      ]
    },
    "engineDependencies": {},
    "preserve": {},
    "postProcess": true
  }
}